easy_geppy/__init__.py
easy_geppy/easy_geppy.py
easy_geppy-0.1.2.dist-info/LICENSE
easy_geppy-0.1.2.dist-info/METADATA
easy_geppy-0.1.2.dist-info/WHEEL
easy_geppy-0.1.2.dist-info/top_level.txt
easy_geppy-0.1.2.dist-info/RECORD
