Metadata-Version: 2.1
Name: easy-geppy
Version: 0.1.2
Summary: EasyGeppy is an easy to use programming interface for Geppy
Home-page: https://github.com/edvieira/EasyGeppy
Author: Eduardo Henrique Vieira dos Santos
Author-email: edvieira@github.com
License: GPL-3.0 license
Platform: UNKNOWN
Classifier: Development Status :: 1 - Planning
Classifier: Intended Audience :: Science/Research
Classifier: License :: OSI Approved :: GNU General Public License v3 or later (GPLv3+)
Classifier: Programming Language :: Python :: 3
License-File: LICENSE
Requires-Dist: deap (>=1.3.3)
Requires-Dist: dill (>=0.3.5.1)
Requires-Dist: geppy (>=0.1.3)
Requires-Dist: numpy
Requires-Dist: pandas (>=1.3.4)
Requires-Dist: sympy
Requires-Dist: graphviz
